package p;

import java.util.ArrayList;
import m.d;

public class b {
  static void a(f paramf, d paramd, int paramInt1, int paramInt2, c paramc) {
    // Byte code:
    //   0: iload_2
    //   1: istore #17
    //   3: aload #4
    //   5: getfield a : Lp/e;
    //   8: astore #23
    //   10: aload #4
    //   12: getfield c : Lp/e;
    //   15: astore #27
    //   17: aload #4
    //   19: getfield b : Lp/e;
    //   22: astore #18
    //   24: aload #4
    //   26: getfield d : Lp/e;
    //   29: astore #25
    //   31: aload #4
    //   33: getfield e : Lp/e;
    //   36: astore #20
    //   38: aload #4
    //   40: getfield k : F
    //   43: fstore #5
    //   45: aload_0
    //   46: getfield Z : [Lp/e$b;
    //   49: iload #17
    //   51: aaload
    //   52: getstatic p/e$b.WRAP_CONTENT : Lp/e$b;
    //   55: if_acmpne -> 64
    //   58: iconst_1
    //   59: istore #13
    //   61: goto -> 67
    //   64: iconst_0
    //   65: istore #13
    //   67: iload #17
    //   69: ifne -> 125
    //   72: aload #20
    //   74: getfield z0 : I
    //   77: istore #12
    //   79: iload #12
    //   81: ifne -> 90
    //   84: iconst_1
    //   85: istore #8
    //   87: goto -> 93
    //   90: iconst_0
    //   91: istore #8
    //   93: iload #12
    //   95: iconst_1
    //   96: if_icmpne -> 105
    //   99: iconst_1
    //   100: istore #9
    //   102: goto -> 108
    //   105: iconst_0
    //   106: istore #9
    //   108: iload #8
    //   110: istore #10
    //   112: iload #9
    //   114: istore #11
    //   116: iload #12
    //   118: iconst_2
    //   119: if_icmpne -> 189
    //   122: goto -> 175
    //   125: aload #20
    //   127: getfield A0 : I
    //   130: istore #12
    //   132: iload #12
    //   134: ifne -> 143
    //   137: iconst_1
    //   138: istore #8
    //   140: goto -> 146
    //   143: iconst_0
    //   144: istore #8
    //   146: iload #12
    //   148: iconst_1
    //   149: if_icmpne -> 158
    //   152: iconst_1
    //   153: istore #9
    //   155: goto -> 161
    //   158: iconst_0
    //   159: istore #9
    //   161: iload #8
    //   163: istore #10
    //   165: iload #9
    //   167: istore #11
    //   169: iload #12
    //   171: iconst_2
    //   172: if_icmpne -> 189
    //   175: iconst_1
    //   176: istore #14
    //   178: iload #8
    //   180: istore #11
    //   182: iload #9
    //   184: istore #12
    //   186: goto -> 200
    //   189: iconst_0
    //   190: istore #14
    //   192: iload #11
    //   194: istore #12
    //   196: iload #10
    //   198: istore #11
    //   200: iconst_0
    //   201: istore #8
    //   203: aload #23
    //   205: astore #21
    //   207: aconst_null
    //   208: astore #26
    //   210: aconst_null
    //   211: astore #22
    //   213: iload #8
    //   215: ifne -> 661
    //   218: aload #21
    //   220: getfield W : [Lp/d;
    //   223: iload_3
    //   224: aaload
    //   225: astore #19
    //   227: iload #14
    //   229: ifeq -> 238
    //   232: iconst_1
    //   233: istore #9
    //   235: goto -> 241
    //   238: iconst_4
    //   239: istore #9
    //   241: aload #19
    //   243: invokevirtual f : ()I
    //   246: istore #10
    //   248: aload #21
    //   250: getfield Z : [Lp/e$b;
    //   253: iload #17
    //   255: aaload
    //   256: astore #26
    //   258: getstatic p/e$b.MATCH_CONSTRAINT : Lp/e$b;
    //   261: astore #24
    //   263: aload #26
    //   265: aload #24
    //   267: if_acmpne -> 287
    //   270: aload #21
    //   272: getfield y : [I
    //   275: iload #17
    //   277: iaload
    //   278: ifne -> 287
    //   281: iconst_1
    //   282: istore #16
    //   284: goto -> 290
    //   287: iconst_0
    //   288: istore #16
    //   290: aload #19
    //   292: getfield f : Lp/d;
    //   295: astore #26
    //   297: iload #10
    //   299: istore #15
    //   301: aload #26
    //   303: ifnull -> 327
    //   306: iload #10
    //   308: istore #15
    //   310: aload #21
    //   312: aload #23
    //   314: if_acmpeq -> 327
    //   317: iload #10
    //   319: aload #26
    //   321: invokevirtual f : ()I
    //   324: iadd
    //   325: istore #15
    //   327: iload #14
    //   329: ifeq -> 353
    //   332: aload #21
    //   334: aload #23
    //   336: if_acmpeq -> 353
    //   339: aload #21
    //   341: aload #18
    //   343: if_acmpeq -> 353
    //   346: bipush #8
    //   348: istore #9
    //   350: goto -> 353
    //   353: aload #19
    //   355: getfield f : Lp/d;
    //   358: astore #26
    //   360: aload #26
    //   362: ifnull -> 485
    //   365: aload #21
    //   367: aload #18
    //   369: if_acmpne -> 393
    //   372: aload_1
    //   373: aload #19
    //   375: getfield i : Lm/i;
    //   378: aload #26
    //   380: getfield i : Lm/i;
    //   383: iload #15
    //   385: bipush #6
    //   387: invokevirtual h : (Lm/i;Lm/i;II)V
    //   390: goto -> 411
    //   393: aload_1
    //   394: aload #19
    //   396: getfield i : Lm/i;
    //   399: aload #26
    //   401: getfield i : Lm/i;
    //   404: iload #15
    //   406: bipush #8
    //   408: invokevirtual h : (Lm/i;Lm/i;II)V
    //   411: iload #9
    //   413: istore #10
    //   415: iload #16
    //   417: ifeq -> 432
    //   420: iload #9
    //   422: istore #10
    //   424: iload #14
    //   426: ifne -> 432
    //   429: iconst_5
    //   430: istore #10
    //   432: aload #21
    //   434: aload #18
    //   436: if_acmpne -> 460
    //   439: iload #14
    //   441: ifeq -> 460
    //   444: aload #21
    //   446: iload #17
    //   448: invokevirtual h0 : (I)Z
    //   451: ifeq -> 460
    //   454: iconst_5
    //   455: istore #10
    //   457: goto -> 460
    //   460: aload_1
    //   461: aload #19
    //   463: getfield i : Lm/i;
    //   466: aload #19
    //   468: getfield f : Lp/d;
    //   471: getfield i : Lm/i;
    //   474: iload #15
    //   476: iload #10
    //   478: invokevirtual e : (Lm/i;Lm/i;II)Lm/b;
    //   481: pop
    //   482: goto -> 485
    //   485: iload #13
    //   487: ifeq -> 571
    //   490: aload #21
    //   492: invokevirtual V : ()I
    //   495: bipush #8
    //   497: if_icmpeq -> 545
    //   500: aload #21
    //   502: getfield Z : [Lp/e$b;
    //   505: iload #17
    //   507: aaload
    //   508: aload #24
    //   510: if_acmpne -> 545
    //   513: aload #21
    //   515: getfield W : [Lp/d;
    //   518: astore #19
    //   520: aload_1
    //   521: aload #19
    //   523: iload_3
    //   524: iconst_1
    //   525: iadd
    //   526: aaload
    //   527: getfield i : Lm/i;
    //   530: aload #19
    //   532: iload_3
    //   533: aaload
    //   534: getfield i : Lm/i;
    //   537: iconst_0
    //   538: iconst_5
    //   539: invokevirtual h : (Lm/i;Lm/i;II)V
    //   542: goto -> 545
    //   545: aload_1
    //   546: aload #21
    //   548: getfield W : [Lp/d;
    //   551: iload_3
    //   552: aaload
    //   553: getfield i : Lm/i;
    //   556: aload_0
    //   557: getfield W : [Lp/d;
    //   560: iload_3
    //   561: aaload
    //   562: getfield i : Lm/i;
    //   565: iconst_0
    //   566: bipush #8
    //   568: invokevirtual h : (Lm/i;Lm/i;II)V
    //   571: aload #21
    //   573: getfield W : [Lp/d;
    //   576: iload_3
    //   577: iconst_1
    //   578: iadd
    //   579: aaload
    //   580: getfield f : Lp/d;
    //   583: astore #24
    //   585: aload #22
    //   587: astore #19
    //   589: aload #24
    //   591: ifnull -> 643
    //   594: aload #24
    //   596: getfield d : Lp/e;
    //   599: astore #24
    //   601: aload #24
    //   603: getfield W : [Lp/d;
    //   606: iload_3
    //   607: aaload
    //   608: getfield f : Lp/d;
    //   611: astore #26
    //   613: aload #22
    //   615: astore #19
    //   617: aload #26
    //   619: ifnull -> 643
    //   622: aload #26
    //   624: getfield d : Lp/e;
    //   627: aload #21
    //   629: if_acmpeq -> 639
    //   632: aload #22
    //   634: astore #19
    //   636: goto -> 643
    //   639: aload #24
    //   641: astore #19
    //   643: aload #19
    //   645: ifnull -> 655
    //   648: aload #19
    //   650: astore #21
    //   652: goto -> 658
    //   655: iconst_1
    //   656: istore #8
    //   658: goto -> 207
    //   661: aload #25
    //   663: ifnull -> 861
    //   666: aload #27
    //   668: getfield W : [Lp/d;
    //   671: astore #19
    //   673: iload_3
    //   674: iconst_1
    //   675: iadd
    //   676: istore #9
    //   678: aload #19
    //   680: iload #9
    //   682: aaload
    //   683: getfield f : Lp/d;
    //   686: ifnull -> 861
    //   689: aload #25
    //   691: getfield W : [Lp/d;
    //   694: iload #9
    //   696: aaload
    //   697: astore #19
    //   699: aload #25
    //   701: getfield Z : [Lp/e$b;
    //   704: iload #17
    //   706: aaload
    //   707: getstatic p/e$b.MATCH_CONSTRAINT : Lp/e$b;
    //   710: if_acmpne -> 730
    //   713: aload #25
    //   715: getfield y : [I
    //   718: iload #17
    //   720: iaload
    //   721: ifne -> 730
    //   724: iconst_1
    //   725: istore #8
    //   727: goto -> 733
    //   730: iconst_0
    //   731: istore #8
    //   733: iload #8
    //   735: ifeq -> 784
    //   738: iload #14
    //   740: ifne -> 784
    //   743: aload #19
    //   745: getfield f : Lp/d;
    //   748: astore #21
    //   750: aload #21
    //   752: getfield d : Lp/e;
    //   755: aload_0
    //   756: if_acmpne -> 784
    //   759: aload_1
    //   760: aload #19
    //   762: getfield i : Lm/i;
    //   765: aload #21
    //   767: getfield i : Lm/i;
    //   770: aload #19
    //   772: invokevirtual f : ()I
    //   775: ineg
    //   776: iconst_5
    //   777: invokevirtual e : (Lm/i;Lm/i;II)Lm/b;
    //   780: pop
    //   781: goto -> 827
    //   784: iload #14
    //   786: ifeq -> 827
    //   789: aload #19
    //   791: getfield f : Lp/d;
    //   794: astore #21
    //   796: aload #21
    //   798: getfield d : Lp/e;
    //   801: aload_0
    //   802: if_acmpne -> 827
    //   805: aload_1
    //   806: aload #19
    //   808: getfield i : Lm/i;
    //   811: aload #21
    //   813: getfield i : Lm/i;
    //   816: aload #19
    //   818: invokevirtual f : ()I
    //   821: ineg
    //   822: iconst_4
    //   823: invokevirtual e : (Lm/i;Lm/i;II)Lm/b;
    //   826: pop
    //   827: aload_1
    //   828: aload #19
    //   830: getfield i : Lm/i;
    //   833: aload #27
    //   835: getfield W : [Lp/d;
    //   838: iload #9
    //   840: aaload
    //   841: getfield f : Lp/d;
    //   844: getfield i : Lm/i;
    //   847: aload #19
    //   849: invokevirtual f : ()I
    //   852: ineg
    //   853: bipush #6
    //   855: invokevirtual j : (Lm/i;Lm/i;II)V
    //   858: goto -> 861
    //   861: iload #13
    //   863: ifeq -> 911
    //   866: aload_0
    //   867: getfield W : [Lp/d;
    //   870: astore_0
    //   871: iload_3
    //   872: iconst_1
    //   873: iadd
    //   874: istore #8
    //   876: aload_0
    //   877: iload #8
    //   879: aaload
    //   880: getfield i : Lm/i;
    //   883: astore_0
    //   884: aload #27
    //   886: getfield W : [Lp/d;
    //   889: iload #8
    //   891: aaload
    //   892: astore #19
    //   894: aload_1
    //   895: aload_0
    //   896: aload #19
    //   898: getfield i : Lm/i;
    //   901: aload #19
    //   903: invokevirtual f : ()I
    //   906: bipush #8
    //   908: invokevirtual h : (Lm/i;Lm/i;II)V
    //   911: aload #4
    //   913: getfield h : Ljava/util/ArrayList;
    //   916: astore_0
    //   917: aload_0
    //   918: ifnull -> 1214
    //   921: aload_0
    //   922: invokevirtual size : ()I
    //   925: istore #8
    //   927: iload #8
    //   929: iconst_1
    //   930: if_icmple -> 1214
    //   933: aload #4
    //   935: getfield r : Z
    //   938: ifeq -> 960
    //   941: aload #4
    //   943: getfield t : Z
    //   946: ifne -> 960
    //   949: aload #4
    //   951: getfield j : I
    //   954: i2f
    //   955: fstore #6
    //   957: goto -> 964
    //   960: fload #5
    //   962: fstore #6
    //   964: aconst_null
    //   965: astore #19
    //   967: iconst_0
    //   968: istore #9
    //   970: fconst_0
    //   971: fstore #7
    //   973: iload #9
    //   975: iload #8
    //   977: if_icmpge -> 1214
    //   980: aload_0
    //   981: iload #9
    //   983: invokevirtual get : (I)Ljava/lang/Object;
    //   986: checkcast p/e
    //   989: astore #21
    //   991: aload #21
    //   993: getfield D0 : [F
    //   996: iload #17
    //   998: faload
    //   999: fstore #5
    //   1001: fload #5
    //   1003: fconst_0
    //   1004: fcmpg
    //   1005: ifge -> 1055
    //   1008: aload #4
    //   1010: getfield t : Z
    //   1013: ifeq -> 1049
    //   1016: aload #21
    //   1018: getfield W : [Lp/d;
    //   1021: astore #21
    //   1023: aload_1
    //   1024: aload #21
    //   1026: iload_3
    //   1027: iconst_1
    //   1028: iadd
    //   1029: aaload
    //   1030: getfield i : Lm/i;
    //   1033: aload #21
    //   1035: iload_3
    //   1036: aaload
    //   1037: getfield i : Lm/i;
    //   1040: iconst_0
    //   1041: iconst_4
    //   1042: invokevirtual e : (Lm/i;Lm/i;II)Lm/b;
    //   1045: pop
    //   1046: goto -> 1093
    //   1049: fconst_1
    //   1050: fstore #5
    //   1052: goto -> 1055
    //   1055: fload #5
    //   1057: fconst_0
    //   1058: fcmpl
    //   1059: ifne -> 1100
    //   1062: aload #21
    //   1064: getfield W : [Lp/d;
    //   1067: astore #21
    //   1069: aload_1
    //   1070: aload #21
    //   1072: iload_3
    //   1073: iconst_1
    //   1074: iadd
    //   1075: aaload
    //   1076: getfield i : Lm/i;
    //   1079: aload #21
    //   1081: iload_3
    //   1082: aaload
    //   1083: getfield i : Lm/i;
    //   1086: iconst_0
    //   1087: bipush #8
    //   1089: invokevirtual e : (Lm/i;Lm/i;II)Lm/b;
    //   1092: pop
    //   1093: fload #7
    //   1095: fstore #5
    //   1097: goto -> 1201
    //   1100: aload #19
    //   1102: ifnull -> 1197
    //   1105: aload #19
    //   1107: getfield W : [Lp/d;
    //   1110: astore #22
    //   1112: aload #22
    //   1114: iload_3
    //   1115: aaload
    //   1116: getfield i : Lm/i;
    //   1119: astore #19
    //   1121: iload_3
    //   1122: iconst_1
    //   1123: iadd
    //   1124: istore #10
    //   1126: aload #22
    //   1128: iload #10
    //   1130: aaload
    //   1131: getfield i : Lm/i;
    //   1134: astore #22
    //   1136: aload #21
    //   1138: getfield W : [Lp/d;
    //   1141: astore #28
    //   1143: aload #28
    //   1145: iload_3
    //   1146: aaload
    //   1147: getfield i : Lm/i;
    //   1150: astore #24
    //   1152: aload #28
    //   1154: iload #10
    //   1156: aaload
    //   1157: getfield i : Lm/i;
    //   1160: astore #28
    //   1162: aload_1
    //   1163: invokevirtual r : ()Lm/b;
    //   1166: astore #29
    //   1168: aload #29
    //   1170: fload #7
    //   1172: fload #6
    //   1174: fload #5
    //   1176: aload #19
    //   1178: aload #22
    //   1180: aload #24
    //   1182: aload #28
    //   1184: invokevirtual l : (FFFLm/i;Lm/i;Lm/i;Lm/i;)Lm/b;
    //   1187: pop
    //   1188: aload_1
    //   1189: aload #29
    //   1191: invokevirtual d : (Lm/b;)V
    //   1194: goto -> 1197
    //   1197: aload #21
    //   1199: astore #19
    //   1201: iload #9
    //   1203: iconst_1
    //   1204: iadd
    //   1205: istore #9
    //   1207: fload #5
    //   1209: fstore #7
    //   1211: goto -> 973
    //   1214: aload #18
    //   1216: ifnull -> 1394
    //   1219: aload #18
    //   1221: aload #25
    //   1223: if_acmpeq -> 1231
    //   1226: iload #14
    //   1228: ifeq -> 1394
    //   1231: aload #23
    //   1233: getfield W : [Lp/d;
    //   1236: iload_3
    //   1237: aaload
    //   1238: astore_0
    //   1239: aload #27
    //   1241: getfield W : [Lp/d;
    //   1244: astore #4
    //   1246: iload_3
    //   1247: iconst_1
    //   1248: iadd
    //   1249: istore_2
    //   1250: aload #4
    //   1252: iload_2
    //   1253: aaload
    //   1254: astore #19
    //   1256: aload_0
    //   1257: getfield f : Lp/d;
    //   1260: astore_0
    //   1261: aload_0
    //   1262: ifnull -> 1273
    //   1265: aload_0
    //   1266: getfield i : Lm/i;
    //   1269: astore_0
    //   1270: goto -> 1275
    //   1273: aconst_null
    //   1274: astore_0
    //   1275: aload #19
    //   1277: getfield f : Lp/d;
    //   1280: astore #4
    //   1282: aload #4
    //   1284: ifnull -> 1297
    //   1287: aload #4
    //   1289: getfield i : Lm/i;
    //   1292: astore #4
    //   1294: goto -> 1300
    //   1297: aconst_null
    //   1298: astore #4
    //   1300: aload #18
    //   1302: getfield W : [Lp/d;
    //   1305: iload_3
    //   1306: aaload
    //   1307: astore #21
    //   1309: aload #25
    //   1311: ifnull -> 1323
    //   1314: aload #25
    //   1316: getfield W : [Lp/d;
    //   1319: iload_2
    //   1320: aaload
    //   1321: astore #19
    //   1323: aload_0
    //   1324: ifnull -> 2423
    //   1327: aload #4
    //   1329: ifnull -> 2423
    //   1332: iload #17
    //   1334: ifne -> 1347
    //   1337: aload #20
    //   1339: getfield o0 : F
    //   1342: fstore #5
    //   1344: goto -> 1354
    //   1347: aload #20
    //   1349: getfield p0 : F
    //   1352: fstore #5
    //   1354: aload #21
    //   1356: invokevirtual f : ()I
    //   1359: istore_2
    //   1360: aload #19
    //   1362: invokevirtual f : ()I
    //   1365: istore #8
    //   1367: aload_1
    //   1368: aload #21
    //   1370: getfield i : Lm/i;
    //   1373: aload_0
    //   1374: iload_2
    //   1375: fload #5
    //   1377: aload #4
    //   1379: aload #19
    //   1381: getfield i : Lm/i;
    //   1384: iload #8
    //   1386: bipush #7
    //   1388: invokevirtual c : (Lm/i;Lm/i;IFLm/i;Lm/i;II)V
    //   1391: goto -> 2423
    //   1394: iload #11
    //   1396: ifeq -> 1853
    //   1399: aload #18
    //   1401: ifnull -> 1853
    //   1404: aload #4
    //   1406: getfield j : I
    //   1409: istore_2
    //   1410: iload_2
    //   1411: ifle -> 1429
    //   1414: aload #4
    //   1416: getfield i : I
    //   1419: iload_2
    //   1420: if_icmpne -> 1429
    //   1423: iconst_1
    //   1424: istore #8
    //   1426: goto -> 1432
    //   1429: iconst_0
    //   1430: istore #8
    //   1432: aload #18
    //   1434: astore #19
    //   1436: aload #19
    //   1438: astore #20
    //   1440: aload #20
    //   1442: ifnull -> 2423
    //   1445: aload #20
    //   1447: getfield F0 : [Lp/e;
    //   1450: iload #17
    //   1452: aaload
    //   1453: astore_0
    //   1454: aload_0
    //   1455: ifnull -> 1478
    //   1458: aload_0
    //   1459: invokevirtual V : ()I
    //   1462: bipush #8
    //   1464: if_icmpne -> 1478
    //   1467: aload_0
    //   1468: getfield F0 : [Lp/e;
    //   1471: iload #17
    //   1473: aaload
    //   1474: astore_0
    //   1475: goto -> 1454
    //   1478: aload_0
    //   1479: ifnonnull -> 1495
    //   1482: aload #20
    //   1484: aload #25
    //   1486: if_acmpne -> 1492
    //   1489: goto -> 1495
    //   1492: goto -> 1826
    //   1495: aload #20
    //   1497: getfield W : [Lp/d;
    //   1500: iload_3
    //   1501: aaload
    //   1502: astore #21
    //   1504: aload #21
    //   1506: getfield i : Lm/i;
    //   1509: astore #24
    //   1511: aload #21
    //   1513: getfield f : Lp/d;
    //   1516: astore #4
    //   1518: aload #4
    //   1520: ifnull -> 1533
    //   1523: aload #4
    //   1525: getfield i : Lm/i;
    //   1528: astore #4
    //   1530: goto -> 1536
    //   1533: aconst_null
    //   1534: astore #4
    //   1536: aload #19
    //   1538: aload #20
    //   1540: if_acmpeq -> 1560
    //   1543: aload #19
    //   1545: getfield W : [Lp/d;
    //   1548: iload_3
    //   1549: iconst_1
    //   1550: iadd
    //   1551: aaload
    //   1552: getfield i : Lm/i;
    //   1555: astore #4
    //   1557: goto -> 1597
    //   1560: aload #20
    //   1562: aload #18
    //   1564: if_acmpne -> 1597
    //   1567: aload #23
    //   1569: getfield W : [Lp/d;
    //   1572: iload_3
    //   1573: aaload
    //   1574: getfield f : Lp/d;
    //   1577: astore #4
    //   1579: aload #4
    //   1581: ifnull -> 1594
    //   1584: aload #4
    //   1586: getfield i : Lm/i;
    //   1589: astore #4
    //   1591: goto -> 1597
    //   1594: aconst_null
    //   1595: astore #4
    //   1597: aload #21
    //   1599: invokevirtual f : ()I
    //   1602: istore #13
    //   1604: aload #20
    //   1606: getfield W : [Lp/d;
    //   1609: astore #21
    //   1611: iload_3
    //   1612: iconst_1
    //   1613: iadd
    //   1614: istore #10
    //   1616: aload #21
    //   1618: iload #10
    //   1620: aaload
    //   1621: invokevirtual f : ()I
    //   1624: istore #9
    //   1626: aload_0
    //   1627: ifnull -> 1648
    //   1630: aload_0
    //   1631: getfield W : [Lp/d;
    //   1634: iload_3
    //   1635: aaload
    //   1636: astore #22
    //   1638: aload #22
    //   1640: getfield i : Lm/i;
    //   1643: astore #21
    //   1645: goto -> 1679
    //   1648: aload #27
    //   1650: getfield W : [Lp/d;
    //   1653: iload #10
    //   1655: aaload
    //   1656: getfield f : Lp/d;
    //   1659: astore #22
    //   1661: aload #22
    //   1663: ifnull -> 1676
    //   1666: aload #22
    //   1668: getfield i : Lm/i;
    //   1671: astore #21
    //   1673: goto -> 1645
    //   1676: aconst_null
    //   1677: astore #21
    //   1679: aload #20
    //   1681: getfield W : [Lp/d;
    //   1684: iload #10
    //   1686: aaload
    //   1687: getfield i : Lm/i;
    //   1690: astore #28
    //   1692: iload #9
    //   1694: istore_2
    //   1695: aload #22
    //   1697: ifnull -> 1709
    //   1700: iload #9
    //   1702: aload #22
    //   1704: invokevirtual f : ()I
    //   1707: iadd
    //   1708: istore_2
    //   1709: iload #13
    //   1711: aload #19
    //   1713: getfield W : [Lp/d;
    //   1716: iload #10
    //   1718: aaload
    //   1719: invokevirtual f : ()I
    //   1722: iadd
    //   1723: istore #9
    //   1725: aload #24
    //   1727: ifnull -> 1823
    //   1730: aload #4
    //   1732: ifnull -> 1823
    //   1735: aload #21
    //   1737: ifnull -> 1823
    //   1740: aload #28
    //   1742: ifnull -> 1823
    //   1745: aload #20
    //   1747: aload #18
    //   1749: if_acmpne -> 1764
    //   1752: aload #18
    //   1754: getfield W : [Lp/d;
    //   1757: iload_3
    //   1758: aaload
    //   1759: invokevirtual f : ()I
    //   1762: istore #9
    //   1764: aload #20
    //   1766: aload #25
    //   1768: if_acmpne -> 1786
    //   1771: aload #25
    //   1773: getfield W : [Lp/d;
    //   1776: iload #10
    //   1778: aaload
    //   1779: invokevirtual f : ()I
    //   1782: istore_2
    //   1783: goto -> 1786
    //   1786: iload #8
    //   1788: ifeq -> 1798
    //   1791: bipush #8
    //   1793: istore #10
    //   1795: goto -> 1801
    //   1798: iconst_5
    //   1799: istore #10
    //   1801: aload_1
    //   1802: aload #24
    //   1804: aload #4
    //   1806: iload #9
    //   1808: ldc 0.5
    //   1810: aload #21
    //   1812: aload #28
    //   1814: iload_2
    //   1815: iload #10
    //   1817: invokevirtual c : (Lm/i;Lm/i;IFLm/i;Lm/i;II)V
    //   1820: goto -> 1826
    //   1823: goto -> 1492
    //   1826: aload #20
    //   1828: invokevirtual V : ()I
    //   1831: bipush #8
    //   1833: if_icmpeq -> 1839
    //   1836: goto -> 1843
    //   1839: aload #19
    //   1841: astore #20
    //   1843: aload #20
    //   1845: astore #19
    //   1847: aload_0
    //   1848: astore #20
    //   1850: goto -> 1440
    //   1853: iload #12
    //   1855: ifeq -> 2423
    //   1858: aload #18
    //   1860: ifnull -> 2423
    //   1863: aload #4
    //   1865: getfield j : I
    //   1868: istore #8
    //   1870: iload #8
    //   1872: ifle -> 1891
    //   1875: aload #4
    //   1877: getfield i : I
    //   1880: iload #8
    //   1882: if_icmpne -> 1891
    //   1885: iconst_1
    //   1886: istore #8
    //   1888: goto -> 1894
    //   1891: iconst_0
    //   1892: istore #8
    //   1894: aload #18
    //   1896: astore #4
    //   1898: aload #4
    //   1900: astore #19
    //   1902: iload_2
    //   1903: istore #9
    //   1905: aload #19
    //   1907: ifnull -> 2263
    //   1910: aload #19
    //   1912: getfield F0 : [Lp/e;
    //   1915: iload #9
    //   1917: aaload
    //   1918: astore_0
    //   1919: aload_0
    //   1920: ifnull -> 1943
    //   1923: aload_0
    //   1924: invokevirtual V : ()I
    //   1927: bipush #8
    //   1929: if_icmpne -> 1943
    //   1932: aload_0
    //   1933: getfield F0 : [Lp/e;
    //   1936: iload #9
    //   1938: aaload
    //   1939: astore_0
    //   1940: goto -> 1919
    //   1943: aload #19
    //   1945: aload #18
    //   1947: if_acmpeq -> 2240
    //   1950: aload #19
    //   1952: aload #25
    //   1954: if_acmpeq -> 2240
    //   1957: aload_0
    //   1958: ifnull -> 2240
    //   1961: aload_0
    //   1962: aload #25
    //   1964: if_acmpne -> 1972
    //   1967: aconst_null
    //   1968: astore_0
    //   1969: goto -> 1972
    //   1972: aload #19
    //   1974: getfield W : [Lp/d;
    //   1977: iload_3
    //   1978: aaload
    //   1979: astore #20
    //   1981: aload #20
    //   1983: getfield i : Lm/i;
    //   1986: astore #28
    //   1988: aload #20
    //   1990: getfield f : Lp/d;
    //   1993: astore #21
    //   1995: aload #21
    //   1997: ifnull -> 2007
    //   2000: aload #21
    //   2002: getfield i : Lm/i;
    //   2005: astore #21
    //   2007: aload #4
    //   2009: getfield W : [Lp/d;
    //   2012: astore #21
    //   2014: iload_3
    //   2015: iconst_1
    //   2016: iadd
    //   2017: istore #14
    //   2019: aload #21
    //   2021: iload #14
    //   2023: aaload
    //   2024: getfield i : Lm/i;
    //   2027: astore #29
    //   2029: aload #20
    //   2031: invokevirtual f : ()I
    //   2034: istore #13
    //   2036: aload #19
    //   2038: getfield W : [Lp/d;
    //   2041: iload #14
    //   2043: aaload
    //   2044: invokevirtual f : ()I
    //   2047: istore #10
    //   2049: aload_0
    //   2050: ifnull -> 2100
    //   2053: aload_0
    //   2054: getfield W : [Lp/d;
    //   2057: iload_3
    //   2058: aaload
    //   2059: astore #21
    //   2061: aload #21
    //   2063: getfield i : Lm/i;
    //   2066: astore #22
    //   2068: aload #21
    //   2070: getfield f : Lp/d;
    //   2073: astore #20
    //   2075: aload #20
    //   2077: ifnull -> 2090
    //   2080: aload #20
    //   2082: getfield i : Lm/i;
    //   2085: astore #20
    //   2087: goto -> 2093
    //   2090: aconst_null
    //   2091: astore #20
    //   2093: aload #20
    //   2095: astore #24
    //   2097: goto -> 2144
    //   2100: aload #25
    //   2102: getfield W : [Lp/d;
    //   2105: iload_3
    //   2106: aaload
    //   2107: astore #21
    //   2109: aload #21
    //   2111: ifnull -> 2124
    //   2114: aload #21
    //   2116: getfield i : Lm/i;
    //   2119: astore #20
    //   2121: goto -> 2127
    //   2124: aconst_null
    //   2125: astore #20
    //   2127: aload #19
    //   2129: getfield W : [Lp/d;
    //   2132: iload #14
    //   2134: aaload
    //   2135: getfield i : Lm/i;
    //   2138: astore #24
    //   2140: aload #20
    //   2142: astore #22
    //   2144: iload #10
    //   2146: istore #9
    //   2148: aload #21
    //   2150: ifnull -> 2163
    //   2153: iload #10
    //   2155: aload #21
    //   2157: invokevirtual f : ()I
    //   2160: iadd
    //   2161: istore #9
    //   2163: aload #4
    //   2165: getfield W : [Lp/d;
    //   2168: iload #14
    //   2170: aaload
    //   2171: invokevirtual f : ()I
    //   2174: istore #14
    //   2176: iload #8
    //   2178: ifeq -> 2188
    //   2181: bipush #8
    //   2183: istore #10
    //   2185: goto -> 2191
    //   2188: iconst_4
    //   2189: istore #10
    //   2191: aload #28
    //   2193: ifnull -> 2237
    //   2196: aload #29
    //   2198: ifnull -> 2237
    //   2201: aload #22
    //   2203: ifnull -> 2237
    //   2206: aload #24
    //   2208: ifnull -> 2237
    //   2211: aload_1
    //   2212: aload #28
    //   2214: aload #29
    //   2216: iload #14
    //   2218: iload #13
    //   2220: iadd
    //   2221: ldc 0.5
    //   2223: aload #22
    //   2225: aload #24
    //   2227: iload #9
    //   2229: iload #10
    //   2231: invokevirtual c : (Lm/i;Lm/i;IFLm/i;Lm/i;II)V
    //   2234: goto -> 2237
    //   2237: goto -> 2240
    //   2240: aload #19
    //   2242: invokevirtual V : ()I
    //   2245: bipush #8
    //   2247: if_icmpeq -> 2257
    //   2250: aload #19
    //   2252: astore #4
    //   2254: goto -> 2257
    //   2257: aload_0
    //   2258: astore #19
    //   2260: goto -> 1902
    //   2263: aload #18
    //   2265: getfield W : [Lp/d;
    //   2268: iload_3
    //   2269: aaload
    //   2270: astore_0
    //   2271: aload #23
    //   2273: getfield W : [Lp/d;
    //   2276: iload_3
    //   2277: aaload
    //   2278: getfield f : Lp/d;
    //   2281: astore #4
    //   2283: aload #25
    //   2285: getfield W : [Lp/d;
    //   2288: astore #19
    //   2290: iload_3
    //   2291: iconst_1
    //   2292: iadd
    //   2293: istore_2
    //   2294: aload #19
    //   2296: iload_2
    //   2297: aaload
    //   2298: astore #19
    //   2300: aload #27
    //   2302: getfield W : [Lp/d;
    //   2305: iload_2
    //   2306: aaload
    //   2307: getfield f : Lp/d;
    //   2310: astore #20
    //   2312: aload #4
    //   2314: ifnull -> 2389
    //   2317: aload #18
    //   2319: aload #25
    //   2321: if_acmpeq -> 2346
    //   2324: aload_1
    //   2325: aload_0
    //   2326: getfield i : Lm/i;
    //   2329: aload #4
    //   2331: getfield i : Lm/i;
    //   2334: aload_0
    //   2335: invokevirtual f : ()I
    //   2338: iconst_5
    //   2339: invokevirtual e : (Lm/i;Lm/i;II)Lm/b;
    //   2342: pop
    //   2343: goto -> 2389
    //   2346: aload #20
    //   2348: ifnull -> 2389
    //   2351: aload_1
    //   2352: aload_0
    //   2353: getfield i : Lm/i;
    //   2356: aload #4
    //   2358: getfield i : Lm/i;
    //   2361: aload_0
    //   2362: invokevirtual f : ()I
    //   2365: ldc 0.5
    //   2367: aload #19
    //   2369: getfield i : Lm/i;
    //   2372: aload #20
    //   2374: getfield i : Lm/i;
    //   2377: aload #19
    //   2379: invokevirtual f : ()I
    //   2382: iconst_5
    //   2383: invokevirtual c : (Lm/i;Lm/i;IFLm/i;Lm/i;II)V
    //   2386: goto -> 2389
    //   2389: aload #20
    //   2391: ifnull -> 2423
    //   2394: aload #18
    //   2396: aload #25
    //   2398: if_acmpeq -> 2423
    //   2401: aload_1
    //   2402: aload #19
    //   2404: getfield i : Lm/i;
    //   2407: aload #20
    //   2409: getfield i : Lm/i;
    //   2412: aload #19
    //   2414: invokevirtual f : ()I
    //   2417: ineg
    //   2418: iconst_5
    //   2419: invokevirtual e : (Lm/i;Lm/i;II)Lm/b;
    //   2422: pop
    //   2423: iload #11
    //   2425: ifne -> 2433
    //   2428: iload #12
    //   2430: ifeq -> 2622
    //   2433: aload #18
    //   2435: ifnull -> 2622
    //   2438: aload #18
    //   2440: aload #25
    //   2442: if_acmpeq -> 2622
    //   2445: aload #18
    //   2447: getfield W : [Lp/d;
    //   2450: astore #22
    //   2452: aload #22
    //   2454: iload_3
    //   2455: aaload
    //   2456: astore #21
    //   2458: aload #25
    //   2460: astore #4
    //   2462: aload #25
    //   2464: ifnonnull -> 2471
    //   2467: aload #18
    //   2469: astore #4
    //   2471: aload #4
    //   2473: getfield W : [Lp/d;
    //   2476: astore_0
    //   2477: iload_3
    //   2478: iconst_1
    //   2479: iadd
    //   2480: istore_3
    //   2481: aload_0
    //   2482: iload_3
    //   2483: aaload
    //   2484: astore #20
    //   2486: aload #21
    //   2488: getfield f : Lp/d;
    //   2491: astore_0
    //   2492: aload_0
    //   2493: ifnull -> 2505
    //   2496: aload_0
    //   2497: getfield i : Lm/i;
    //   2500: astore #19
    //   2502: goto -> 2508
    //   2505: aconst_null
    //   2506: astore #19
    //   2508: aload #20
    //   2510: getfield f : Lp/d;
    //   2513: astore_0
    //   2514: aload_0
    //   2515: ifnull -> 2526
    //   2518: aload_0
    //   2519: getfield i : Lm/i;
    //   2522: astore_0
    //   2523: goto -> 2528
    //   2526: aconst_null
    //   2527: astore_0
    //   2528: aload #27
    //   2530: aload #4
    //   2532: if_acmpeq -> 2561
    //   2535: aload #27
    //   2537: getfield W : [Lp/d;
    //   2540: iload_3
    //   2541: aaload
    //   2542: getfield f : Lp/d;
    //   2545: astore #23
    //   2547: aload #26
    //   2549: astore_0
    //   2550: aload #23
    //   2552: ifnull -> 2561
    //   2555: aload #23
    //   2557: getfield i : Lm/i;
    //   2560: astore_0
    //   2561: aload #18
    //   2563: aload #4
    //   2565: if_acmpne -> 2574
    //   2568: aload #22
    //   2570: iload_3
    //   2571: aaload
    //   2572: astore #20
    //   2574: aload #19
    //   2576: ifnull -> 2622
    //   2579: aload_0
    //   2580: ifnull -> 2622
    //   2583: aload #21
    //   2585: invokevirtual f : ()I
    //   2588: istore_2
    //   2589: aload #4
    //   2591: getfield W : [Lp/d;
    //   2594: iload_3
    //   2595: aaload
    //   2596: invokevirtual f : ()I
    //   2599: istore_3
    //   2600: aload_1
    //   2601: aload #21
    //   2603: getfield i : Lm/i;
    //   2606: aload #19
    //   2608: iload_2
    //   2609: ldc 0.5
    //   2611: aload_0
    //   2612: aload #20
    //   2614: getfield i : Lm/i;
    //   2617: iload_3
    //   2618: iconst_5
    //   2619: invokevirtual c : (Lm/i;Lm/i;IFLm/i;Lm/i;II)V
    //   2622: return
  }
  
  public static void b(f paramf, d paramd, ArrayList<e> paramArrayList, int paramInt) {
    int i;
    byte b1;
    c[] arrayOfC;
    int j = 0;
    if (paramInt == 0) {
      i = paramf.W0;
      arrayOfC = paramf.Z0;
      b1 = 0;
    } else {
      i = paramf.X0;
      arrayOfC = paramf.Y0;
      b1 = 2;
    } 
    while (j < i) {
      c c = arrayOfC[j];
      c.a();
      if (paramArrayList == null || paramArrayList.contains(c.a))
        a(paramf, paramd, paramInt, b1, c); 
      j++;
    } 
  }
}


/* Location:              C:\Users\Pooya\Desktop\smartpek\Smart-dex2jar.jar!\p\b.class
 * Java compiler version: 6 (50.0)
 * JD-Core Version:       1.1.3
 */